README.md
setup.py
bklv2/__init__.py
bklv2/api.py
bklv2.egg-info/PKG-INFO
bklv2.egg-info/SOURCES.txt
bklv2.egg-info/dependency_links.txt
bklv2.egg-info/requires.txt
bklv2.egg-info/top_level.txt