Metadata-Version: 2.1
Name: bklv2
Version: 0.2.0
Summary: Backlog API v2 library
Home-page: https://github.com/etecor/bklv2
Author: etecor
License: MIT
Platform: UNKNOWN
Classifier: Development Status :: 2 - Pre-Alpha
Classifier: Intended Audience :: Developers
Classifier: License :: OSI Approved :: MIT License
Classifier: Programming Language :: Python :: 3
